megakit/__init__.py
megakit/color_operations.py
megakit/file_operations.py
megakit/image_operations.py
megakit/list_operations.py
megakit/random_data_operations.py
megakit/string_operations.py
megakit/system_operations.py
megakit/time_operations.py
megakit-1.0.dist-info/LICENSE
megakit-1.0.dist-info/METADATA
megakit-1.0.dist-info/WHEEL
megakit-1.0.dist-info/top_level.txt
megakit-1.0.dist-info/RECORD
