Metadata-Version: 2.1
Name: megakit
Version: 1.0
Home-page: https://github.com/talalzeini/megakit
Author: Talal El Zeini
Author-email: talalzeini@icloud.com
License: MIT
License-File: LICENSE
